consumptionbackend/__init__.py
consumptionbackend/database/__init__.py
consumptionbackend/database/base.py
consumptionbackend/database/consumable.py
consumptionbackend/database/fields.py
consumptionbackend/database/personnel.py
consumptionbackend/database/queries.py
consumptionbackend/database/series.py
consumptionbackend/database/sqlite/__init__.py
consumptionbackend/database/sqlite/consumable.py
consumptionbackend/database/sqlite/engine.py
consumptionbackend/database/sqlite/helper.py
consumptionbackend/database/sqlite/migrations/v3.0.0.sql
consumptionbackend/database/sqlite/personnel.py
consumptionbackend/database/sqlite/register.py
consumptionbackend/database/sqlite/series.py
consumptionbackend/database/sqlite/sql_utils.py
consumptionbackend/database/sqlite/tag.py
consumptionbackend/database/tag.py
consumptionbackend/entities/__init__.py
consumptionbackend/entities/base.py
consumptionbackend/entities/consumable.py
consumptionbackend/entities/personnel.py
consumptionbackend/entities/series.py
consumptionbackend/entities/status.py
consumptionbackend/entities/types.py
consumptionbackend/py.typed
consumptionbackend/utils/__init__.py
consumptionbackend/utils/exceptions.py
consumptionbackend/utils/services.py
consumptionbackend-3.1.0.dist-info/WHEEL
consumptionbackend-3.1.0.dist-info/METADATA
consumptionbackend-3.1.0.dist-info/RECORD
