Metadata-Version: 2.3
Name: consumptionbackend
Version: 3.1.0
Summary: The backend (SQLite) database manager for the ConsumptionCLI tool.
Author: track44
Author-email: track44 <trackfortyfour@proton.me>
License:                     GNU GENERAL PUBLIC LICENSE
Classifier: Development Status :: 4 - Beta
Classifier: Programming Language :: Python :: 3
Classifier: Programming Language :: SQL
Classifier: License :: OSI Approved :: GNU General Public License v3 (GPLv3)
Classifier: Operating System :: OS Independent
Classifier: Natural Language :: English
Requires-Python: >=3.14
Project-URL: Homepage, https://github.com/track-44/consumptionbackend
Project-URL: Bug Tracker, https://github.com/track-44/consumptionbackend/issues
